ibhax_pack/__init__.py
ibhax_pack/ibhax_pack.py
ibhax_pack/main.py
tests/__init__.py
ibhax_pack-1.0.0.dist-info/METADATA
ibhax_pack-1.0.0.dist-info/WHEEL
ibhax_pack-1.0.0.dist-info/entry_points.txt
ibhax_pack-1.0.0.dist-info/top_level.txt
ibhax_pack-1.0.0.dist-info/RECORD
